{
  "project_info": {
    "project_number": "830338990221",
    "firebase_url": "https://sam-app-446ee.firebaseio.com",
    "project_id": "sam-app-446ee",
    "storage_bucket": "sam-app-446ee.appspot.com"
  },
  "client": [
    {
      "client_info": {
        "mobilesdk_app_id": "1:830338990221:android:8382bb597361e56bcde2c4",
        "android_client_info": {
          "package_name": "com.nelsonsolorzano.appsam"
        }
      },
      "oauth_client": [
        {
          "client_id": "830338990221-tbfm8u88m3oe5grfri2hjq91grt7slob.apps.googleusercontent.com",
          "client_type": 3
        }
      ],
      "api_key": [
        {
          "current_key": "AIzaSyDM9WiecvY-fDYACeehxNaFI1Ons8v64ww"
        }
      ],
      "services": {
        "appinvite_service": {
          "other_platform_oauth_client": [
            {
              "client_id": "830338990221-tbfm8u88m3oe5grfri2hjq91grt7slob.apps.googleusercontent.com",
              "client_type": 3
            }
          ]
        }
      }
    }
  ],
  "configuration_version": "1"
}